django_saas_email/__init__.py
django_saas_email/admin.py
django_saas_email/apps.py
django_saas_email/logger.py
django_saas_email/models.py
django_saas_email/tasks.py
django_saas_email/urls.py
django_saas_email/utils.py
django_saas_email/views.py
django_saas_email/migrations/0001_initial.py
django_saas_email/migrations/0002_add_hello_template.py
django_saas_email/migrations/0003_auto_20181016_1827.py
django_saas_email/migrations/0004_mail_cc_address.py
django_saas_email/migrations/0005_mail_bcc_address.py
django_saas_email/migrations/0006_add_to_and_from_names.py
django_saas_email/migrations/0007_mailtemplate_sender_email.py
django_saas_email/migrations/__init__.py
django_saas_email/templates/django_saas_email/email_base.html
django_saas_email/templates/django_saas_email/footer.html
django_saas_email-0.1.30.dist-info/LICENSE
django_saas_email-0.1.30.dist-info/METADATA
django_saas_email-0.1.30.dist-info/WHEEL
django_saas_email-0.1.30.dist-info/top_level.txt
django_saas_email-0.1.30.dist-info/RECORD
