Metadata-Version: 2.1
Name: django-saas-email
Version: 0.1.30
Summary: An email manager for sending emails with templates, mail history and admin.
Home-page: https://github.com/unicorn-supplies/django-saas-email
Author: Jens Neuhaus
Author-email: kontakt@jensneuhaus.de
License: MIT
Keywords: django-saas-email
Platform: UNKNOWN
Classifier: Development Status :: 3 - Alpha
Classifier: Framework :: Django
Classifier: Framework :: Django :: 1.10
Classifier: Framework :: Django :: 1.11
Classifier: Intended Audience :: Developers
Classifier: License :: OSI Approved :: MIT License
Classifier: Natural Language :: English
Classifier: Programming Language :: Python :: 3.5
Classifier: Programming Language :: Python :: 3.6
Classifier: Programming Language :: Python :: 3 :: Only
Classifier: Programming Language :: Python :: Implementation :: CPython
Classifier: Programming Language :: Python :: Implementation :: PyPy
Classifier: Topic :: Communications :: Email
Requires-Dist: celery (>=4.0)
Requires-Dist: django-anymail
Requires-Dist: django-tinymce
Requires-Dist: django-rq
Requires-Dist: html2text (==2018.1.9)
Requires-Dist: sendgrid
